example_cli/__init__.py
example_cli/__main__.py
example_cli/commands/__init__.py
example_cli/commands/maths.py
example_cli/commands/print.py
firehelper/__init__.py
firehelper/firehelper.py
fire_cli_helper-0.2.dist-info/LICENSE
fire_cli_helper-0.2.dist-info/METADATA
fire_cli_helper-0.2.dist-info/WHEEL
fire_cli_helper-0.2.dist-info/entry_points.txt
fire_cli_helper-0.2.dist-info/top_level.txt
fire_cli_helper-0.2.dist-info/RECORD
