Metadata-Version: 2.1
Name: fire-cli-helper
Version: 0.2
Summary: UNKNOWN
Home-page: https://github.com/frogrammer/fire-cli-helper
Author: Luke Vinton
Author-email: luke0vinton@gmail.com
License: Apache 2.0
Platform: UNKNOWN
Requires-Dist: fire
